local_openai2anthropic/__init__.py
local_openai2anthropic/__main__.py
local_openai2anthropic/config.py
local_openai2anthropic/converter.py
local_openai2anthropic/daemon.py
local_openai2anthropic/daemon_runner.py
local_openai2anthropic/main.py
local_openai2anthropic/openai_types.py
local_openai2anthropic/protocol.py
local_openai2anthropic/router.py
local_openai2anthropic/tavily_client.py
local_openai2anthropic/server_tools/__init__.py
local_openai2anthropic/server_tools/base.py
local_openai2anthropic/server_tools/web_search.py
local_openai2anthropic-0.2.5.dist-info/METADATA
local_openai2anthropic-0.2.5.dist-info/WHEEL
local_openai2anthropic-0.2.5.dist-info/entry_points.txt
local_openai2anthropic-0.2.5.dist-info/licenses/LICENSE
local_openai2anthropic-0.2.5.dist-info/RECORD
