Metadata-Version: 2.4
Name: local-openai2anthropic
Version: 0.2.5
Summary: A lightweight proxy server that converts Anthropic Messages API to OpenAI API
Project-URL: Homepage, https://github.com/dongfangzan/local-openai2anthropic
Project-URL: Repository, https://github.com/dongfangzan/local-openai2anthropic
Project-URL: Issues, https://github.com/dongfangzan/local-openai2anthropic/issues
Author-email: dongfangzan <zsybook0124@163.com>
Maintainer-email: dongfangzan <zsybook0124@163.com>
License: Apache-2.0
License-File: LICENSE
Keywords: anthropic,api,claude,messages,openai,proxy
Classifier: Development Status :: 4 - Beta
Classifier: Intended Audience :: Developers
Classifier: License :: OSI Approved :: Apache Software License
Classifier: Programming Language :: Python :: 3
Classifier: Programming Language :: Python :: 3.12
Classifier: Programming Language :: Python :: 3.13
Classifier: Topic :: Software Development :: Libraries :: Python Modules
Requires-Python: >=3.12
Requires-Dist: anthropic>=0.30.0
Requires-Dist: fastapi>=0.100.0
Requires-Dist: httpx>=0.25.0
Requires-Dist: openai>=1.30.0
Requires-Dist: pydantic-settings>=2.0.0
Requires-Dist: pydantic>=2.0.0
Requires-Dist: uvicorn[standard]>=0.23.0
Provides-Extra: dev
Requires-Dist: black>=23.0.0; extra == 'dev'
Requires-Dist: mypy>=1.0.0; extra == 'dev'
Requires-Dist: pytest-asyncio>=0.21.0; extra == 'dev'
Requires-Dist: pytest>=7.0.0; extra == 'dev'
Requires-Dist: ruff>=0.1.0; extra == 'dev'
